epss_api/__init__.py
epss_api/epss.py
epss_api-1.3.9.dist-info/LICENSE
epss_api-1.3.9.dist-info/METADATA
epss_api-1.3.9.dist-info/WHEEL
epss_api-1.3.9.dist-info/RECORD
