Metadata-Version: 2.3
Name: epss-api
Version: 1.3.9
Summary: EPSS API Python Client
License: MIT
Keywords: EPSS,security,vulnerability
Author: kannkyo
Author-email: 15080890+kannkyo@users.noreply.github.com
Requires-Python: >=3.8,<4.0
Classifier: License :: OSI Approved :: MIT License
Classifier: Programming Language :: Python :: 3
Classifier: Programming Language :: Python :: 3.8
Classifier: Programming Language :: Python :: 3.9
Classifier: Programming Language :: Python :: 3.10
Classifier: Programming Language :: Python :: 3.11
Classifier: Programming Language :: Python :: 3.12
Classifier: Programming Language :: Python :: 3.13
Classifier: Topic :: Security
Classifier: Topic :: Software Development :: Libraries :: Python Modules
Requires-Dist: urllib3 (>=1.26.13,<3.0.0)
Project-URL: Documentation, https://github.com/kannkyo/epss-api
Project-URL: Homepage, https://github.com/kannkyo/epss-api
Project-URL: Repository, https://github.com/kannkyo/epss-api
